LICENSE.txt
MANIFEST.in
README.md
setup.py
tastyworks/__init__.py
tastyworks/example.py
tastyworks/streamer.py
tastyworks.egg-info/PKG-INFO
tastyworks.egg-info/SOURCES.txt
tastyworks.egg-info/dependency_links.txt
tastyworks.egg-info/entry_points.txt
tastyworks.egg-info/requires.txt
tastyworks.egg-info/top_level.txt
tastyworks/dough/__init__.py
tastyworks/dough/stocks.py
tastyworks/dough/watchlists.py
tastyworks/dxfeed/__init__.py
tastyworks/dxfeed/greeks.py
tastyworks/dxfeed/mapped_item.py
tastyworks/dxfeed/mapper.py
tastyworks/dxfeed/quote.py
tastyworks/models/__init__.py
tastyworks/models/option.py
tastyworks/models/option_chain.py
tastyworks/models/order.py
tastyworks/models/security.py
tastyworks/models/session.py
tastyworks/models/trading_account.py
tastyworks/models/underlying.py
tastyworks/tastyworks_api/__init__.py
tastyworks/tastyworks_api/symbols.py
tastyworks/tastyworks_api/tasty_session.py