Metadata-Version: 2.1
Name: tastyworks
Version: 3.0.1
Summary: Tastyworks (unofficial) API
Home-page: http://pypi.python.org/pypi/tastyworks/
Author: Boyan Soubachov
Author-email: boyanvs@gmail.com
License: LICENSE.txt
Keywords: tastyworks,trading,api,algorithmic
Platform: UNKNOWN
Classifier: Development Status :: 3 - Alpha
Classifier: Programming Language :: Python :: 3
Classifier: License :: OSI Approved :: Apache Software License
Classifier: Operating System :: OS Independent
Requires-Python: >= 3.6.0
Provides-Extra: testing
